rk_sdk/__init__.py
rk_sdk/api_client.py
rk_sdk/api_response.py
rk_sdk/configuration.py
rk_sdk/exceptions.py
rk_sdk/py.typed
rk_sdk/rest.py
rk_sdk/api/__init__.py
rk_sdk/api/default_api.py
rk_sdk/models/__init__.py
rk_sdk/models/get_password_200_response.py
rk_sdk-1.0.0.dist-info/METADATA
rk_sdk-1.0.0.dist-info/WHEEL
rk_sdk-1.0.0.dist-info/entry_points.txt
rk_sdk-1.0.0.dist-info/top_level.txt
rk_sdk-1.0.0.dist-info/RECORD
